[
  {
    "id": "73225458-1dc8-4835-8877-91375cedf988",
    "timestamp": "2025-07-15T21:30:20.166610",
    "user_input": "Help me brainstorm ideas for my college essay. I need to write about a challenge I've overcome, but I'm not sure which experience to focus on.",
    "reasoning_steps": [
      {
        "step_number": 1,
        "thought": "",
        "tool_considered": null,
        "confidence": 0.9,
        "context_used": []
      },
      {
        "step_number": 2,
        "thought": "",
        "tool_considered": null,
        "confidence": 0.5,
        "context_used": []
      }
    ],
    "final_action": "tool_execution",
    "result": null,
    "success": true,
    "execution_time": 0.0,
    "context_tokens": 0
  },
  {
    "id": "628019b9-acaa-4e32-8b75-b245ae65c738",
    "timestamp": "2025-07-15T21:40:22.198044",
    "user_input": "Help me brainstorm ideas for my college essay. I need to write about a challenge I've overcome, but I'm not sure which experience to focus on.",
    "reasoning_steps": [
      {
        "step_number": 1,
        "thought": "",
        "tool_considered": null,
        "confidence": 0.9,
        "context_used": []
      },
      {
        "step_number": 2,
        "thought": "",
        "tool_considered": null,
        "confidence": 0.5,
        "context_used": []
      }
    ],
    "final_action": "tool_execution",
    "result": null,
    "success": true,
    "execution_time": 0.0,
    "context_tokens": 0
  },
  {
    "id": "b80ab668-5f0e-45ac-a101-a05120941a7a",
    "timestamp": "2025-07-15T21:41:22.837433",
    "user_input": "I really like the public speaking anxiety story! I was terrified to give presentations but joined Model UN and eventually became our school's delegate to state competition. How should I structure this story to make it compelling?",
    "reasoning_steps": [
      {
        "step_number": 1,
        "thought": "",
        "tool_considered": null,
        "confidence": 0.8,
        "context_used": []
      },
      {
        "step_number": 2,
        "thought": "",
        "tool_considered": null,
        "confidence": 0.5,
        "context_used": []
      }
    ],
    "final_action": "error",
    "result": null,
    "success": false,
    "execution_time": 0.0,
    "context_tokens": 0
  },
  {
    "id": "c22f8958-bf79-45df-bef7-2fce35845107",
    "timestamp": "2025-07-15T22:17:57.714710",
    "user_input": "I need help writing an essay about my leadership experience in robotics club for Stanford University. Can you help me brainstorm some ideas?",
    "reasoning_steps": [
      {
        "step_number": 1,
        "thought": "",
        "tool_considered": null,
        "confidence": 0.9,
        "context_used": []
      },
      {
        "step_number": 2,
        "thought": "",
        "tool_considered": null,
        "confidence": 0.5,
        "context_used": []
      }
    ],
    "final_action": "tool_execution",
    "result": null,
    "success": true,
    "execution_time": 0.0,
    "context_tokens": 0
  },
  {
    "id": "bca8b3c7-6e41-4763-830a-1be295ef7e59",
    "timestamp": "2025-07-15T22:36:41.614202",
    "user_input": "Help me brainstorm my Stanford essay about overcoming challenge. I want to write about when i did well in my calcculus class despite it being hard",
    "reasoning_steps": [
      {
        "step_number": 1,
        "thought": "",
        "tool_considered": null,
        "confidence": 0.9,
        "context_used": []
      },
      {
        "step_number": 2,
        "thought": "",
        "tool_considered": null,
        "confidence": 0.5,
        "context_used": []
      }
    ],
    "final_action": "tool_execution",
    "result": null,
    "success": true,
    "execution_time": 0.0,
    "context_tokens": 0
  },
  {
    "id": "cca57977-193b-4fe9-902e-cc4651e552c4",
    "timestamp": "2025-07-15T22:38:14.827686",
    "user_input": "Develop a draft of story 1 Conquering Calculus Challenges.",
    "reasoning_steps": [
      {
        "step_number": 1,
        "thought": "",
        "tool_considered": null,
        "confidence": 0.8,
        "context_used": []
      },
      {
        "step_number": 2,
        "thought": "",
        "tool_considered": null,
        "confidence": 0.5,
        "context_used": []
      }
    ],
    "final_action": "tool_execution",
    "result": null,
    "success": true,
    "execution_time": 0.0,
    "context_tokens": 0
  },
  {
    "id": "d159a580-a9d8-4a15-81f3-4f90bdfc087e",
    "timestamp": "2025-07-15T22:39:39.601336",
    "user_input": "Lets brainstorm what I could use as the hook. Give me a few examples of things that may have happened",
    "reasoning_steps": [
      {
        "step_number": 1,
        "thought": "",
        "tool_considered": null,
        "confidence": 0.8,
        "context_used": []
      },
      {
        "step_number": 2,
        "thought": "",
        "tool_considered": null,
        "confidence": 0.5,
        "context_used": []
      }
    ],
    "final_action": "tool_execution",
    "result": null,
    "success": true,
    "execution_time": 0.0,
    "context_tokens": 0
  },
  {
    "id": "722654ee-0ba4-45de-a4cf-00403e9e654e",
    "timestamp": "2025-07-15T22:40:29.890230",
    "user_input": "But its about over coming calculus",
    "reasoning_steps": [
      {
        "step_number": 1,
        "thought": "",
        "tool_considered": null,
        "confidence": 0.9,
        "context_used": []
      },
      {
        "step_number": 2,
        "thought": "",
        "tool_considered": null,
        "confidence": 0.5,
        "context_used": []
      }
    ],
    "final_action": "tool_execution",
    "result": null,
    "success": true,
    "execution_time": 0.0,
    "context_tokens": 0
  }
]